aer/__init__.py
aerpy-0.4.dist-info/LICENSE
aerpy-0.4.dist-info/METADATA
aerpy-0.4.dist-info/WHEEL
aerpy-0.4.dist-info/top_level.txt
aerpy-0.4.dist-info/RECORD
